[
  {
    "sapling": 3134,
    "orchard": 0,
    "timestamp": "2024-09-05T19:11:11.440662Z"
  },
  {
    "sprout": 0,
    "sapling": 946,
    "orchard": 192,
    "timestamp": "10/25/2024"
  },
  {
    "sprout": 0,
    "sapling": 926,
    "orchard": 159,
    "timestamp": "10/26/2024"
  },
  {
    "sprout": 0,
    "sapling": 958,
    "orchard": 150,
    "timestamp": "10/27/2024"
  },
  {
    "sprout": 0,
    "sapling": 923,
    "orchard": 235,
    "timestamp": "10/28/2024"
  },
  {
    "sprout": 0,
    "sapling": 934,
    "orchard": 208,
    "timestamp": "10/30/2024"
  },
  {
    "sprout": 0,
    "sapling": 945,
    "orchard": 172,
    "timestamp": "11/01/2024"
  },
  {
    "sprout": 0,
    "sapling": 914,
    "orchard": 159,
    "timestamp": "11/02/2024"
  },
  {
    "sprout": 0,
    "sapling": 955,
    "orchard": 159,
    "timestamp": "11/03/2024"
  },
  {
    "sprout": 0,
    "sapling": 967,
    "orchard": 258,
    "timestamp": "11/04/2024"
  },
  {
    "sprout": 0,
    "sapling": 187,
    "orchard": 290,
    "timestamp": "11/06/2024"
  },
  {
    "sprout": 0,
    "sapling": 126,
    "orchard": 263,
    "timestamp": "11/07/2024"
  },
  {
    "sprout": 0,
    "sapling": 131,
    "orchard": 200,
    "timestamp": "11/09/2024"
  },
  {
    "sprout": 0,
    "sapling": 134,
    "orchard": 192,
    "timestamp": "11/10/2024"
  },
  {
    "sprout": 0,
    "sapling": 138,
    "orchard": 196,
    "timestamp": "11/11/2024"
  },
  {
    "sprout": 10,
    "sapling": 257,
    "orchard": 194,
    "timestamp": "11/13/2024"
  },
  {
    "sprout": 5,
    "sapling": 227,
    "orchard": 221,
    "timestamp": "11/14/2024"
  },
  {
    "sprout": 2,
    "sapling": 285,
    "orchard": 250,
    "timestamp": "11/15/2024"
  },
  {
    "sprout": 1,
    "sapling": 165,
    "orchard": 255,
    "timestamp": "11/16/2024"
  },
  {
    "sprout": 0,
    "sapling": 146,
    "orchard": 261,
    "timestamp": "11/17/2024"
  },
  {
    "sprout": 0,
    "sapling": 146,
    "orchard": 247,
    "timestamp": "11/19/2024"
  },
  {
    "sprout": 0,
    "sapling": 174,
    "orchard": 310,
    "timestamp": "11/20/2024"
  },
  {
    "sprout": 0,
    "sapling": 156,
    "orchard": 188,
    "timestamp": "11/22/2024"
  },
  {
    "sprout": 0,
    "sapling": 131,
    "orchard": 201,
    "timestamp": "11/25/2024"
  },
  {
    "sprout": 0,
    "sapling": 165,
    "orchard": 275,
    "timestamp": "11/26/2024"
  },
  {
    "sprout": 0,
    "sapling": 191,
    "orchard": 301,
    "timestamp": "11/27/2024"
  },
  {
    "sprout": 0,
    "sapling": 131,
    "orchard": 271,
    "timestamp": "11/28/2024"
  },
  {
    "sprout": 0,
    "sapling": 127,
    "orchard": 260,
    "timestamp": "11/29/2024"
  },
  {
    "sprout": 0,
    "sapling": 110,
    "orchard": 296,
    "timestamp": "11/30/2024"
  },
  {
    "sprout": 0,
    "sapling": 106,
    "orchard": 313,
    "timestamp": "11/30/2024"
  },
  {
    "sprout": 1,
    "sapling": 142,
    "orchard": 252,
    "timestamp": "12/01/2024"
  },
  {
    "sprout": 0,
    "sapling": 185,
    "orchard": 224,
    "timestamp": "12/02/2024"
  },
  {
    "sprout": 0,
    "sapling": 204,
    "orchard": 298,
    "timestamp": "12/03/2024"
  },
  {
    "sprout": 0,
    "sapling": 169,
    "orchard": 267,
    "timestamp": "12/04/2024"
  },
  {
    "sprout": 0,
    "sapling": 164,
    "orchard": 210,
    "timestamp": "12/05/2024"
  },
  {
    "sprout": 0,
    "sapling": 133,
    "orchard": 238,
    "timestamp": "12/06/2024"
  },
  {
    "sprout": 0,
    "sapling": 129,
    "orchard": 234,
    "timestamp": "12/07/2024"
  },
  {
    "sprout": 0,
    "sapling": 171,
    "orchard": 241,
    "timestamp": "12/09/2024"
  },
  {
    "sprout": 0,
    "sapling": 152,
    "orchard": 198,
    "timestamp": "12/10/2024"
  },
  {
    "sprout": 1,
    "sapling": 176,
    "orchard": 208,
    "timestamp": "12/11/2024"
  },
  {
    "sprout": 2,
    "sapling": 119,
    "orchard": 242,
    "timestamp": "12/12/2024"
  },
  {
    "sprout": 3,
    "sapling": 122,
    "orchard": 226,
    "timestamp": "12/13/2024"
  },
  {
    "sprout": 2,
    "sapling": 96,
    "orchard": 239,
    "timestamp": "12/14/2024"
  },
  {
    "sprout": 2,
    "sapling": 93,
    "orchard": 180,
    "timestamp": "12/15/2024"
  },
  {
    "sprout": 2,
    "sapling": 147,
    "orchard": 216,
    "timestamp": "12/17/2024"
  },
  {
    "sprout": 2,
    "sapling": 180,
    "orchard": 247,
    "timestamp": "12/18/2024"
  },
  {
    "sprout": 2,
    "sapling": 180,
    "orchard": 245,
    "timestamp": "12/18/2024"
  },
  {
    "sprout": 2,
    "sapling": 153,
    "orchard": 240,
    "timestamp": "12/18/2024"
  },
  {
    "sprout": 1,
    "sapling": 134,
    "orchard": 211,
    "timestamp": "12/19/2024"
  },
  {
    "sprout": 0,
    "sapling": 177,
    "orchard": 313,
    "timestamp": "12/20/2024"
  },
  {
    "sprout": 0,
    "sapling": 136,
    "orchard": 215,
    "timestamp": "12/21/2024"
  },
  {
    "sprout": 0,
    "sapling": 128,
    "orchard": 239,
    "timestamp": "12/22/2024"
  },
  {
    "sprout": 0,
    "sapling": 148,
    "orchard": 208,
    "timestamp": "12/23/2024"
  },
  {
    "sprout": 0,
    "sapling": 136,
    "orchard": 271,
    "timestamp": "12/24/2024"
  },
  {
    "sprout": 0,
    "sapling": 179,
    "orchard": 242,
    "timestamp": "12/25/2024"
  },
  {
    "sprout": 0,
    "sapling": 145,
    "orchard": 260,
    "timestamp": "12/26/2024"
  },
  {
    "sprout": 0,
    "sapling": 156,
    "orchard": 335,
    "timestamp": "12/27/2024"
  },
  {
    "sprout": 0,
    "sapling": 167,
    "orchard": 310,
    "timestamp": "12/28/2024"
  },
  {
    "sprout": 0,
    "sapling": 137,
    "orchard": 357,
    "timestamp": "12/29/2024"
  },
  {
    "sprout": 0,
    "sapling": 146,
    "orchard": 296,
    "timestamp": "12/30/2024"
  },
  {
    "sprout": 0,
    "sapling": 146,
    "orchard": 274,
    "timestamp": "12/31/2024"
  },
  {
    "sprout": 0,
    "sapling": 94,
    "orchard": 213,
    "timestamp": "01/01/2025"
  },
  {
    "sprout": 2,
    "sapling": 141,
    "orchard": 240,
    "timestamp": "01/02/2025"
  },
  {
    "sprout": 7,
    "sapling": 155,
    "orchard": 252,
    "timestamp": "01/03/2025"
  },
  {
    "sprout": 2,
    "sapling": 139,
    "orchard": 256,
    "timestamp": "01/05/2025"
  },
  {
    "sprout": 3,
    "sapling": 156,
    "orchard": 272,
    "timestamp": "01/06/2025"
  },
  {
    "sprout": 2,
    "sapling": 174,
    "orchard": 248,
    "timestamp": "01/07/2025"
  },
  {
    "sprout": 0,
    "sapling": 125,
    "orchard": 243,
    "timestamp": "01/08/2025"
  },
  {
    "sprout": 0,
    "sapling": 128,
    "orchard": 237,
    "timestamp": "01/11/2025"
  },
  {
    "sprout": 1,
    "sapling": 147,
    "orchard": 263,
    "timestamp": "01/12/2025"
  },
  {
    "sprout": 0,
    "sapling": 184,
    "orchard": 205,
    "timestamp": "01/13/2025"
  },
  {
    "sprout": 0,
    "sapling": 193,
    "orchard": 353,
    "timestamp": "01/14/2025"
  },
  {
    "sprout": 0,
    "sapling": 166,
    "orchard": 337,
    "timestamp": "01/15/2025"
  }
]
